datatidy/__init__.py
datatidy/cli.py
datatidy/core.py
datatidy/join_engine.py
datatidy/config/__init__.py
datatidy/config/parser.py
datatidy/config/schema.py
datatidy/input/__init__.py
datatidy/input/readers.py
datatidy/transformation/__init__.py
datatidy/transformation/column_operations.py
datatidy/transformation/dependency_resolver.py
datatidy/transformation/engine.py
datatidy/transformation/expressions.py
datatidy-1.0.1.dist-info/licenses/LICENSE
datatidy-1.0.1.dist-info/METADATA
datatidy-1.0.1.dist-info/WHEEL
datatidy-1.0.1.dist-info/entry_points.txt
datatidy-1.0.1.dist-info/top_level.txt
datatidy-1.0.1.dist-info/RECORD
