Metadata-Version: 2.4
Name: datatidy
Version: 1.0.1
Summary: A powerful, configuration-driven data processing and cleaning package
Home-page: https://github.com/wwd1015/datatidy
Author: DataTidy Development Team
Author-email: DataTidy Development Team <maintainer@example.com>
Maintainer-email: DataTidy Development Team <maintainer@example.com>
License: MIT
Project-URL: Homepage, https://github.com/wwd1015/datatidy
Project-URL: Documentation, https://github.com/wwd1015/datatidy#readme
Project-URL: Repository, https://github.com/wwd1015/datatidy
Project-URL: Bug Reports, https://github.com/wwd1015/datatidy/issues
Project-URL: Changelog, https://github.com/wwd1015/datatidy/blob/main/CHANGELOG.md
Keywords: data processing,data cleaning,ETL,configuration-driven,pandas,data transformation
Classifier: Development Status :: 5 - Production/Stable
Classifier: Intended Audience :: Developers
Classifier: Intended Audience :: Science/Research
Classifier: Topic :: Scientific/Engineering :: Information Analysis
Classifier: Topic :: Software Development :: Libraries :: Python Modules
Classifier: License :: OSI Approved :: MIT License
Classifier: Operating System :: OS Independent
Classifier: Programming Language :: Python :: 3
Classifier: Programming Language :: Python :: 3.8
Classifier: Programming Language :: Python :: 3.9
Classifier: Programming Language :: Python :: 3.10
Classifier: Programming Language :: Python :: 3.11
Classifier: Programming Language :: Python :: 3.12
Requires-Python: >=3.8
License-File: LICENSE
Requires-Dist: pandas>=1.5.0
Requires-Dist: PyYAML>=6.0
Requires-Dist: sqlalchemy>=1.4.0
Requires-Dist: openpyxl>=3.0.0
Requires-Dist: snowflake-sqlalchemy>=1.4.0
Requires-Dist: psycopg2-binary>=2.9.0
Requires-Dist: pymysql>=1.0.0
Requires-Dist: jsonschema>=4.0.0
Provides-Extra: dev
Requires-Dist: pytest>=7.0.0; extra == "dev"
Requires-Dist: pytest-cov>=4.0.0; extra == "dev"
Requires-Dist: black>=22.0.0; extra == "dev"
Requires-Dist: flake8>=5.0.0; extra == "dev"
Requires-Dist: mypy>=1.0.0; extra == "dev"
Provides-Extra: all
Requires-Dist: pyarrow>=10.0.0; extra == "all"
Requires-Dist: fastparquet>=0.8.0; extra == "all"
Dynamic: author
Dynamic: home-page
Dynamic: license-file
Dynamic: requires-python
